{
    "2025-02-01": [
        [
            "tide.low",
            "00:23",
            "0.99m",
            "---"
        ],
        [
            "tide.high",
            "06:29",
            "6.4m",
            "99"
        ],
        [
            "tide.low",
            "12:46",
            "0.83m",
            "---"
        ],
        [
            "tide.high",
            "18:47",
            "6.01m",
            "98"
        ]
    ],
    "2025-02-02": [
        [
            "tide.low",
            "01:04",
            "0.97m",
            "---"
        ],
        [
            "tide.high",
            "07:08",
            "6.3m",
            "96"
        ],
        [
            "tide.low",
            "13:27",
            "0.91m",
            "---"
        ],
        [
            "tide.high",
            "19:24",
            "5.84m",
            "93"
        ]
    ],
    "2025-02-03": [
        [
            "tide.low",
            "01:47",
            "1.09m",
            "---"
        ],
        [
            "tide.high",
            "07:50",
            "6.06m",
            "89"
        ],
        [
            "tide.low",
            "14:11",
            "1.15m",
            "---"
        ],
        [
            "tide.high",
            "20:03",
            "5.57m",
            "84"
        ]
    ],
    "2025-02-04": [
        [
            "tide.low",
            "02:33",
            "1.34m",
            "---"
        ],
        [
            "tide.high",
            "08:36",
            "5.7m",
            "78"
        ],
        [
            "tide.low",
            "14:58",
            "1.5m",
            "---"
        ],
        [
            "tide.high",
            "20:51",
            "5.24m",
            "71"
        ]
    ],
    "2025-02-05": [
        [
            "tide.low",
            "03:24",
            "1.69m",
            "---"
        ],
        [
            "tide.high",
            "09:44",
            "5.29m",
            "64"
        ],
        [
            "tide.low",
            "15:51",
            "1.92m",
            "---"
        ],
        [
            "tide.high",
            "22:40",
            "4.95m",
            "57"
        ]
    ],
    "2025-02-06": [
        [
            "tide.low",
            "04:22",
            "2.07m",
            "---"
        ],
        [
            "tide.high",
            "11:33",
            "5.01m",
            "50"
        ],
        [
            "tide.low",
            "16:54",
            "2.31m",
            "---"
        ]
    ],
    "2025-02-07": [
        [
            "tide.low",
            "05:33",
            "2.36m",
            "---"
        ],
        [
            "tide.high",
            "00:22",
            "4.89m",
            "46"
        ],
        [
            "tide.low",
            "18:09",
            "2.53m",
            "---"
        ],
        [
            "tide.high",
            "13:03",
            "4.97m",
            "43"
        ]
    ],
    "2025-02-08": [
        [
            "tide.low",
            "06:55",
            "2.42m",
            "---"
        ],
        [
            "tide.high",
            "01:39",
            "5.03m",
            "43"
        ],
        [
            "tide.low",
            "19:31",
            "2.46m",
            "---"
        ],
        [
            "tide.high",
            "14:16",
            "5.11m",
            "46"
        ]
    ],
    "2025-02-09": [
        [
            "tide.low",
            "08:16",
            "2.19m",
            "---"
        ],
        [
            "tide.high",
            "02:43",
            "5.28m",
            "50"
        ],
        [
            "tide.low",
            "20:42",
            "2.17m",
            "---"
        ],
        [
            "tide.high",
            "15:13",
            "5.34m",
            "56"
        ]
    ],
    "2025-02-10": [
        [
            "tide.low",
            "09:19",
            "1.83m",
            "---"
        ],
        [
            "tide.high",
            "03:34",
            "5.55m",
            "62"
        ],
        [
            "tide.low",
            "21:37",
            "1.82m",
            "---"
        ],
        [
            "tide.high",
            "15:58",
            "5.56m",
            "68"
        ]
    ],
    "2025-02-11": [
        [
            "tide.low",
            "10:10",
            "1.49m",
            "---"
        ],
        [
            "tide.high",
            "04:15",
            "5.78m",
            "74"
        ],
        [
            "tide.low",
            "22:24",
            "1.52m",
            "---"
        ],
        [
            "tide.high",
            "16:34",
            "5.73m",
            "78"
        ]
    ],
    "2025-02-12": [
        [
            "tide.low",
            "10:53",
            "1.25m",
            "---"
        ],
        [
            "tide.high",
            "04:48",
            "5.95m",
            "82"
        ],
        [
            "tide.low",
            "23:05",
            "1.31m",
            "---"
        ],
        [
            "tide.high",
            "17:04",
            "5.84m",
            "86"
        ]
    ],
    "2025-02-13": [
        [
            "tide.low",
            "11:32",
            "1.13m",
            "---"
        ],
        [
            "tide.high",
            "05:15",
            "6.05m",
            "88"
        ],
        [
            "tide.low",
            "23:42",
            "1.22m",
            "---"
        ],
        [
            "tide.high",
            "17:28",
            "5.9m",
            "89"
        ]
    ],
    "2025-02-14": [
        [
            "tide.high",
            "05:38",
            "6.09m",
            "90"
        ],
        [
            "tide.low",
            "12:07",
            "1.12m",
            "---"
        ],
        [
            "tide.high",
            "17:50",
            "5.9m",
            "90"
        ]
    ],
    "2025-02-15": [
        [
            "tide.low",
            "00:17",
            "1.22m",
            "---"
        ],
        [
            "tide.high",
            "06:01",
            "6.06m",
            "89"
        ],
        [
            "tide.low",
            "12:40",
            "1.23m",
            "---"
        ],
        [
            "tide.high",
            "18:14",
            "5.84m",
            "87"
        ]
    ],
    "2025-02-16": [
        [
            "tide.low",
            "00:50",
            "1.33m",
            "---"
        ],
        [
            "tide.high",
            "06:27",
            "5.96m",
            "84"
        ],
        [
            "tide.low",
            "13:12",
            "1.42m",
            "---"
        ],
        [
            "tide.high",
            "18:41",
            "5.71m",
            "80"
        ]
    ],
    "2025-02-17": [
        [
            "tide.low",
            "01:23",
            "1.53m",
            "---"
        ],
        [
            "tide.high",
            "06:54",
            "5.77m",
            "76"
        ],
        [
            "tide.low",
            "13:43",
            "1.69m",
            "---"
        ],
        [
            "tide.high",
            "19:08",
            "5.5m",
            "72"
        ]
    ],
    "2025-02-18": [
        [
            "tide.low",
            "01:55",
            "1.79m",
            "---"
        ],
        [
            "tide.high",
            "07:20",
            "5.5m",
            "67"
        ],
        [
            "tide.low",
            "14:15",
            "2m",
            "---"
        ],
        [
            "tide.high",
            "19:36",
            "5.24m",
            "61"
        ]
    ],
    "2025-02-19": [
        [
            "tide.low",
            "02:29",
            "2.09m",
            "---"
        ],
        [
            "tide.high",
            "07:46",
            "5.19m",
            "56"
        ],
        [
            "tide.low",
            "14:50",
            "2.34m",
            "---"
        ],
        [
            "tide.high",
            "20:06",
            "4.95m",
            "49"
        ]
    ],
    "2025-02-20": [
        [
            "tide.low",
            "03:08",
            "2.41m",
            "---"
        ],
        [
            "tide.high",
            "08:15",
            "4.86m",
            "44"
        ],
        [
            "tide.low",
            "15:30",
            "2.68m",
            "---"
        ],
        [
            "tide.high",
            "20:50",
            "4.65m",
            "38"
        ]
    ],
    "2025-02-21": [
        [
            "tide.low",
            "03:54",
            "2.72m",
            "---"
        ],
        [
            "tide.high",
            "08:59",
            "4.53m",
            "32"
        ],
        [
            "tide.low",
            "16:24",
            "2.98m",
            "---"
        ],
        [
            "tide.high",
            "23:40",
            "4.5m",
            "28"
        ]
    ],
    "2025-02-22": [
        [
            "tide.low",
            "04:56",
            "2.96m",
            "---"
        ],
        [
            "tide.low",
            "17:42",
            "3.13m",
            "---"
        ],
        [
            "tide.high",
            "12:35",
            "4.41m",
            "25"
        ]
    ],
    "2025-02-23": [
        [
            "tide.low",
            "06:22",
            "2.98m",
            "---"
        ],
        [
            "tide.high",
            "01:05",
            "4.67m",
            "26"
        ],
        [
            "tide.low",
            "19:18",
            "2.96m",
            "---"
        ],
        [
            "tide.high",
            "13:52",
            "4.64m",
            "30"
        ]
    ],
    "2025-02-24": [
        [
            "tide.low",
            "07:49",
            "2.68m",
            "---"
        ],
        [
            "tide.high",
            "02:05",
            "4.97m",
            "36"
        ],
        [
            "tide.low",
            "20:24",
            "2.55m",
            "---"
        ],
        [
            "tide.high",
            "14:45",
            "4.98m",
            "44"
        ]
    ],
    "2025-02-25": [
        [
            "tide.low",
            "08:49",
            "2.19m",
            "---"
        ],
        [
            "tide.high",
            "02:53",
            "5.35m",
            "52"
        ],
        [
            "tide.low",
            "21:14",
            "2.04m",
            "---"
        ],
        [
            "tide.high",
            "15:27",
            "5.37m",
            "60"
        ]
    ],
    "2025-02-26": [
        [
            "tide.low",
            "09:37",
            "1.66m",
            "---"
        ],
        [
            "tide.high",
            "03:36",
            "5.76m",
            "69"
        ],
        [
            "tide.low",
            "21:58",
            "1.54m",
            "---"
        ],
        [
            "tide.high",
            "16:04",
            "5.74m",
            "77"
        ]
    ],
    "2025-02-27": [
        [
            "tide.low",
            "10:20",
            "1.16m",
            "---"
        ],
        [
            "tide.high",
            "04:15",
            "6.14m",
            "85"
        ],
        [
            "tide.low",
            "22:40",
            "1.09m",
            "---"
        ],
        [
            "tide.high",
            "16:39",
            "6.05m",
            "92"
        ]
    ],
    "2025-02-28": [
        [
            "tide.low",
            "11:02",
            "0.76m",
            "---"
        ],
        [
            "tide.high",
            "04:53",
            "6.46m",
            "99"
        ],
        [
            "tide.low",
            "23:21",
            "0.75m",
            "---"
        ],
        [
            "tide.high",
            "17:13",
            "6.28m",
            "104"
        ]
    ]
}