{
    "2025-06-01": [
        [
            "tide.low",
            "03:18",
            "1.62m",
            "---"
        ],
        [
            "tide.high",
            "09:57",
            "5.06m",
            "63"
        ],
        [
            "tide.low",
            "15:36",
            "2.02m",
            "---"
        ],
        [
            "tide.high",
            "22:18",
            "5.22m",
            "58"
        ]
    ],
    "2025-06-02": [
        [
            "tide.low",
            "04:13",
            "1.94m",
            "---"
        ],
        [
            "tide.high",
            "11:09",
            "4.87m",
            "53"
        ],
        [
            "tide.low",
            "16:32",
            "2.28m",
            "---"
        ],
        [
            "tide.high",
            "23:31",
            "5.05m",
            "49"
        ]
    ],
    "2025-06-03": [
        [
            "tide.low",
            "05:10",
            "2.21m",
            "---"
        ],
        [
            "tide.low",
            "17:32",
            "2.45m",
            "---"
        ],
        [
            "tide.high",
            "12:18",
            "4.79m",
            "46"
        ]
    ],
    "2025-06-04": [
        [
            "tide.low",
            "06:11",
            "2.37m",
            "---"
        ],
        [
            "tide.high",
            "00:37",
            "4.95m",
            "44"
        ],
        [
            "tide.low",
            "18:35",
            "2.52m",
            "---"
        ],
        [
            "tide.high",
            "13:19",
            "4.8m",
            "43"
        ]
    ],
    "2025-06-05": [
        [
            "tide.low",
            "07:14",
            "2.42m",
            "---"
        ],
        [
            "tide.high",
            "01:36",
            "4.93m",
            "43"
        ],
        [
            "tide.low",
            "19:37",
            "2.48m",
            "---"
        ],
        [
            "tide.high",
            "14:08",
            "4.89m",
            "44"
        ]
    ],
    "2025-06-06": [
        [
            "tide.low",
            "08:12",
            "2.36m",
            "---"
        ],
        [
            "tide.high",
            "02:26",
            "4.96m",
            "46"
        ],
        [
            "tide.low",
            "20:33",
            "2.37m",
            "---"
        ],
        [
            "tide.high",
            "14:49",
            "5.02m",
            "48"
        ]
    ],
    "2025-06-07": [
        [
            "tide.low",
            "09:04",
            "2.24m",
            "---"
        ],
        [
            "tide.high",
            "03:07",
            "5.04m",
            "51"
        ],
        [
            "tide.low",
            "21:22",
            "2.23m",
            "---"
        ],
        [
            "tide.high",
            "15:24",
            "5.18m",
            "53"
        ]
    ],
    "2025-06-08": [
        [
            "tide.low",
            "09:48",
            "2.12m",
            "---"
        ],
        [
            "tide.high",
            "03:44",
            "5.14m",
            "56"
        ],
        [
            "tide.low",
            "22:05",
            "2.09m",
            "---"
        ],
        [
            "tide.high",
            "15:58",
            "5.33m",
            "59"
        ]
    ],
    "2025-06-09": [
        [
            "tide.low",
            "10:28",
            "2.01m",
            "---"
        ],
        [
            "tide.high",
            "04:19",
            "5.25m",
            "61"
        ],
        [
            "tide.low",
            "22:45",
            "1.95m",
            "---"
        ],
        [
            "tide.high",
            "16:32",
            "5.47m",
            "64"
        ]
    ],
    "2025-06-10": [
        [
            "tide.low",
            "11:05",
            "1.91m",
            "---"
        ],
        [
            "tide.high",
            "04:53",
            "5.34m",
            "66"
        ],
        [
            "tide.low",
            "23:24",
            "1.82m",
            "---"
        ],
        [
            "tide.high",
            "17:05",
            "5.57m",
            "67"
        ]
    ],
    "2025-06-11": [
        [
            "tide.low",
            "11:41",
            "1.85m",
            "---"
        ],
        [
            "tide.high",
            "05:27",
            "5.4m",
            "69"
        ],
        [
            "tide.high",
            "17:39",
            "5.64m",
            "70"
        ]
    ],
    "2025-06-12": [
        [
            "tide.low",
            "00:01",
            "1.73m",
            "---"
        ],
        [
            "tide.high",
            "06:00",
            "5.42m",
            "71"
        ],
        [
            "tide.low",
            "12:18",
            "1.82m",
            "---"
        ],
        [
            "tide.high",
            "18:14",
            "5.67m",
            "71"
        ]
    ],
    "2025-06-13": [
        [
            "tide.low",
            "00:39",
            "1.67m",
            "---"
        ],
        [
            "tide.high",
            "06:34",
            "5.41m",
            "71"
        ],
        [
            "tide.low",
            "12:55",
            "1.83m",
            "---"
        ],
        [
            "tide.high",
            "18:51",
            "5.67m",
            "71"
        ]
    ],
    "2025-06-14": [
        [
            "tide.low",
            "01:17",
            "1.66m",
            "---"
        ],
        [
            "tide.high",
            "07:10",
            "5.37m",
            "70"
        ],
        [
            "tide.low",
            "13:33",
            "1.88m",
            "---"
        ],
        [
            "tide.high",
            "19:32",
            "5.62m",
            "70"
        ]
    ],
    "2025-06-15": [
        [
            "tide.low",
            "01:57",
            "1.69m",
            "---"
        ],
        [
            "tide.high",
            "07:51",
            "5.3m",
            "68"
        ],
        [
            "tide.low",
            "14:14",
            "1.95m",
            "---"
        ],
        [
            "tide.high",
            "20:19",
            "5.55m",
            "67"
        ]
    ],
    "2025-06-16": [
        [
            "tide.low",
            "02:39",
            "1.76m",
            "---"
        ],
        [
            "tide.high",
            "08:39",
            "5.2m",
            "65"
        ],
        [
            "tide.low",
            "14:58",
            "2.04m",
            "---"
        ],
        [
            "tide.high",
            "21:13",
            "5.46m",
            "63"
        ]
    ],
    "2025-06-17": [
        [
            "tide.low",
            "03:24",
            "1.85m",
            "---"
        ],
        [
            "tide.high",
            "09:39",
            "5.1m",
            "61"
        ],
        [
            "tide.low",
            "15:46",
            "2.13m",
            "---"
        ],
        [
            "tide.high",
            "22:15",
            "5.37m",
            "59"
        ]
    ],
    "2025-06-18": [
        [
            "tide.low",
            "04:14",
            "1.94m",
            "---"
        ],
        [
            "tide.high",
            "10:51",
            "5.03m",
            "58"
        ],
        [
            "tide.low",
            "16:41",
            "2.19m",
            "---"
        ],
        [
            "tide.high",
            "23:22",
            "5.32m",
            "56"
        ]
    ],
    "2025-06-19": [
        [
            "tide.low",
            "05:11",
            "2m",
            "---"
        ],
        [
            "tide.low",
            "17:42",
            "2.19m",
            "---"
        ],
        [
            "tide.high",
            "12:06",
            "5.05m",
            "56"
        ]
    ],
    "2025-06-20": [
        [
            "tide.low",
            "06:13",
            "2.01m",
            "---"
        ],
        [
            "tide.high",
            "00:31",
            "5.33m",
            "56"
        ],
        [
            "tide.low",
            "18:46",
            "2.1m",
            "---"
        ],
        [
            "tide.high",
            "13:15",
            "5.16m",
            "57"
        ]
    ],
    "2025-06-21": [
        [
            "tide.low",
            "07:18",
            "1.93m",
            "---"
        ],
        [
            "tide.high",
            "01:38",
            "5.41m",
            "58"
        ],
        [
            "tide.low",
            "19:51",
            "1.92m",
            "---"
        ],
        [
            "tide.high",
            "14:17",
            "5.33m",
            "61"
        ]
    ],
    "2025-06-22": [
        [
            "tide.low",
            "08:22",
            "1.77m",
            "---"
        ],
        [
            "tide.high",
            "02:41",
            "5.53m",
            "64"
        ],
        [
            "tide.low",
            "20:54",
            "1.68m",
            "---"
        ],
        [
            "tide.high",
            "15:13",
            "5.54m",
            "67"
        ]
    ],
    "2025-06-23": [
        [
            "tide.low",
            "09:22",
            "1.59m",
            "---"
        ],
        [
            "tide.high",
            "03:40",
            "5.67m",
            "71"
        ],
        [
            "tide.low",
            "21:54",
            "1.43m",
            "---"
        ],
        [
            "tide.high",
            "16:06",
            "5.74m",
            "75"
        ]
    ],
    "2025-06-24": [
        [
            "tide.low",
            "10:19",
            "1.41m",
            "---"
        ],
        [
            "tide.high",
            "04:36",
            "5.8m",
            "78"
        ],
        [
            "tide.low",
            "22:51",
            "1.21m",
            "---"
        ],
        [
            "tide.high",
            "16:56",
            "5.9m",
            "82"
        ]
    ],
    "2025-06-25": [
        [
            "tide.low",
            "11:12",
            "1.29m",
            "---"
        ],
        [
            "tide.high",
            "05:28",
            "5.88m",
            "84"
        ],
        [
            "tide.low",
            "23:45",
            "1.06m",
            "---"
        ],
        [
            "tide.high",
            "17:45",
            "6m",
            "86"
        ]
    ],
    "2025-06-26": [
        [
            "tide.high",
            "06:18",
            "5.89m",
            "87"
        ],
        [
            "tide.low",
            "12:03",
            "1.24m",
            "---"
        ],
        [
            "tide.high",
            "18:32",
            "6.03m",
            "88"
        ]
    ],
    "2025-06-27": [
        [
            "tide.low",
            "00:36",
            "1.01m",
            "---"
        ],
        [
            "tide.high",
            "07:04",
            "5.82m",
            "88"
        ],
        [
            "tide.low",
            "12:52",
            "1.26m",
            "---"
        ],
        [
            "tide.high",
            "19:17",
            "5.97m",
            "86"
        ]
    ],
    "2025-06-28": [
        [
            "tide.low",
            "01:25",
            "1.06m",
            "---"
        ],
        [
            "tide.high",
            "07:46",
            "5.67m",
            "85"
        ],
        [
            "tide.low",
            "13:39",
            "1.36m",
            "---"
        ],
        [
            "tide.high",
            "19:57",
            "5.84m",
            "82"
        ]
    ],
    "2025-06-29": [
        [
            "tide.low",
            "02:12",
            "1.21m",
            "---"
        ],
        [
            "tide.high",
            "08:24",
            "5.48m",
            "79"
        ],
        [
            "tide.low",
            "14:26",
            "1.53m",
            "---"
        ],
        [
            "tide.high",
            "20:32",
            "5.65m",
            "75"
        ]
    ],
    "2025-06-30": [
        [
            "tide.low",
            "02:57",
            "1.44m",
            "---"
        ],
        [
            "tide.high",
            "08:56",
            "5.27m",
            "71"
        ],
        [
            "tide.low",
            "15:12",
            "1.76m",
            "---"
        ],
        [
            "tide.high",
            "21:04",
            "5.44m",
            "67"
        ]
    ]
}